easy_slurm/__init__.py
easy_slurm/format.py
easy_slurm/jobs.py
easy_slurm/templates/__init__.py
easy_slurm/templates/job.sh
easy_slurm/templates/job_interactive.sh
easy_slurm-0.2.2.dist-info/LICENSE
easy_slurm-0.2.2.dist-info/METADATA
easy_slurm-0.2.2.dist-info/WHEEL
easy_slurm-0.2.2.dist-info/RECORD
