Metadata-Version: 2.1
Name: easy-slurm
Version: 0.2.2
Summary: Easily manage and submit robust jobs to Slurm using Python and Bash.
Home-page: https://github.com/YodaEmbedding/easy-slurm
License: MIT
Keywords: slurm,sbatch
Author: Mateen Ulhaq
Author-email: mulhaq2005@gmail.com
Requires-Python: >=3.7,<4.0
Classifier: License :: OSI Approved :: MIT License
Classifier: Programming Language :: Python :: 3
Classifier: Programming Language :: Python :: 3.7
Classifier: Programming Language :: Python :: 3.8
Classifier: Programming Language :: Python :: 3.9
Classifier: Programming Language :: Python :: 3.10
Classifier: Programming Language :: Python :: 3.11
Project-URL: Repository, https://github.com/YodaEmbedding/easy-slurm
